django_list_wrestler/__init__.py
django_list_wrestler/admin.py
django_list_wrestler/static/django_list_wrestler/css/django-list-wrestler-collapsible.css
django_list_wrestler/static/django_list_wrestler/css/django-list-wrestler-orderable.css
django_list_wrestler/static/django_list_wrestler/css/django-skin-collapsible.css
django_list_wrestler/static/django_list_wrestler/css/django-skin-orderable.css
django_list_wrestler/static/django_list_wrestler/css/grappelli-skin-collapsible.css
django_list_wrestler/static/django_list_wrestler/css/grappelli-skin-orderable.css
django_list_wrestler/static/django_list_wrestler/images/icons-s846f870921.png
django_list_wrestler/static/django_list_wrestler/js/django-list-wrestler-collapsible.js
django_list_wrestler/static/django_list_wrestler/js/django-list-wrestler-orderable.js
django_list_wrestler-6.3.dist-info/AUTHORS.rst
django_list_wrestler-6.3.dist-info/LICENSE.txt
django_list_wrestler-6.3.dist-info/METADATA
django_list_wrestler-6.3.dist-info/WHEEL
django_list_wrestler-6.3.dist-info/top_level.txt
django_list_wrestler-6.3.dist-info/RECORD
