Metadata-Version: 2.1
Name: django-list-wrestler
Version: 6.3
Summary: Make django admin lists easier to sort and collapse.
Home-page: https://github.com/ninapavlich/django-list-wrestler
Author: Nina Pavlich
Author-email: nina@ninalp.com
License: BSD
Platform: UNKNOWN
Classifier: Development Status :: 4 - Beta
Classifier: Environment :: Web Environment
Classifier: Framework :: Django
Classifier: Intended Audience :: Developers
Classifier: License :: OSI Approved
Classifier: Operating System :: OS Independent
Classifier: Programming Language :: Python
